setup.py
jbash/__init__.py
jbash.egg-info/PKG-INFO
jbash.egg-info/SOURCES.txt
jbash.egg-info/dependency_links.txt
jbash.egg-info/top_level.txt