Metadata-Version: 1.0
Name: jbash
Version: 2.2.2
Summary: Provide a magic for jupyter notebooks to run interactive bash shells
Home-page: http://cct.lsu.edu/~sbrandt/
Author: Steven R. Brandt
Author-email: steven@stevenrbrandt.com
License: LGPL
Platform: UNKNOWN
